httpyserver/RequestHandler.py
httpyserver/ResponseManagers.py
httpyserver/ResponseManagers_Exceptions.py
httpyserver/Server.py
httpyserver/Server_Exceptions.py
httpyserver/__init__.py
httpyserver/base.py
httpyserver/constants.py
httpyserver/mongo.py
httpyserver/mongo_utils.py
httpyserver/utilities.py
httpyserver-1.0.1.dist-info/licenses/LICENSE.txt
httpyserver-1.0.1.dist-info/METADATA
httpyserver-1.0.1.dist-info/WHEEL
httpyserver-1.0.1.dist-info/top_level.txt
httpyserver-1.0.1.dist-info/RECORD
