Metadata-Version: 2.4
Name: HTTPyServer
Version: 1.0.1
Summary: A package to create your python HTTP server with no effort
Home-page: https://github.com/odm2-6/httpyserver
Author: odm2-6
Author-email: odm2.letter@gmail.com
Project-URL: Bug Tracker, https://github.com/odm2-6/httpyserver/issues
Project-URL: repository, https://github.com/odm2-6/httpyserver
Classifier: Programming Language :: Python :: 3
Classifier: License :: OSI Approved :: MIT License
Classifier: Operating System :: OS Independent
Requires-Python: >=3.9
License-File: LICENSE.txt
Requires-Dist: pydantic
Requires-Dist: pymongo
Requires-Dist: requests
Dynamic: license-file
